commons/__init__.py
commons/admin.py
commons/apps.py
commons/models.py
commons/tests.py
commons/views.py
commons/migrations/__init__.py
commons/python/__init__.py
commons/python/core/__init__.py
commons/python/core/help/__init__.py
commons/python/core/help/format.py
commons/templates/commons/components/cards.html
commons/templates/commons/components/clear-card.html
commons/templates/commons/components/messages.html
commons/templates/commons/components/navigator.html
commons/templates/commons/components/pagination.html
commons/templatetags/__init__.py
commons/templatetags/uifilters.py
commons_app_base-0.3.dist-info/LICENSE
commons_app_base-0.3.dist-info/METADATA
commons_app_base-0.3.dist-info/WHEEL
commons_app_base-0.3.dist-info/top_level.txt
commons_app_base-0.3.dist-info/RECORD
